solid_broccoli/__init__.py
solid_broccoli/__main__.py
solid_broccoli/convert.py
solid_broccoli-0.0.1.dist-info/LICENSE
solid_broccoli-0.0.1.dist-info/METADATA
solid_broccoli-0.0.1.dist-info/WHEEL
solid_broccoli-0.0.1.dist-info/entry_points.txt
solid_broccoli-0.0.1.dist-info/top_level.txt
solid_broccoli-0.0.1.dist-info/RECORD
