Metadata-Version: 2.1
Name: solid-broccoli
Version: 0.0.1
Summary: Unix timestamp to Human readable format and backwards
Author: IM-coding
Author-email: im_coding <imcodingproj@gmail.com>
Project-URL: Homepage, https://github.com/IM-coding/solid-broccoli
Project-URL: Bug Tracker, https://github.com/IM-coding/solid-broccoli/issues
Classifier: Programming Language :: Python :: 3
Classifier: License :: OSI Approved :: MIT License
Classifier: Operating System :: OS Independent
Requires-Python: >=3.7
License-File: LICENSE
Requires-Dist: python-dateutil
